dcorelib/__init__.py
dcorelib/sparse_gf/__init__.py
dcorelib/sparse_gf/basis.py
dcorelib/sparse_gf/high_freq.py
dcorelib/sparse_gf/transform.py
dcorelib/triqs_compat/__init__.py
dcorelib/triqs_compat/dft_tools/__init__.py
dcorelib/triqs_compat/dft_tools/block_structure.py
dcorelib/triqs_compat/dft_tools/root_finding.py
dcorelib/triqs_compat/dft_tools/sumk_dft.py
dcorelib/triqs_compat/dft_tools/sumk_dft_tools.py
dcorelib/triqs_compat/dft_tools/symmetry.py
dcorelib/triqs_compat/dft_tools/converters/__init__.py
dcorelib/triqs_compat/dft_tools/converters/converter_tools.py
dcorelib/triqs_compat/dft_tools/converters/hk.py
dcorelib/triqs_compat/dft_tools/converters/wannier90.py
dcorelib/triqs_compat/gf/__init__.py
dcorelib/triqs_compat/gf/block_gf.py
dcorelib/triqs_compat/gf/gf.py
dcorelib/triqs_compat/gf/meshes.py
dcorelib/triqs_compat/gf/tools.py
dcorelib/triqs_compat/gf/plot/__init__.py
dcorelib/triqs_compat/gf/plot/one_var.py
dcorelib/triqs_compat/gf/plot/plot_base.py
dcorelib/triqs_compat/gf/plot/select_indices.py
dcorelib/triqs_compat/h5/__init__.py
dcorelib/triqs_compat/h5/archive.py
dcorelib/triqs_compat/h5/archive_basic_layer.py
dcorelib/triqs_compat/h5/formats.py
dcorelib/triqs_compat/h5/version.py
dcorelib/triqs_compat/mpi/__init__.py
dcorelib/triqs_compat/mpi/_mpi.py
dcorelib/triqs_compat/mpi/_no_mpi.py
dcorelib/triqs_compat/mpi/mpi.py
dcorelib/triqs_compat/operators/__init__.py
dcorelib/triqs_compat/operators/util/U_matrix.py
dcorelib/triqs_compat/operators/util/__init__.py
dcorelib/triqs_compat/operators/util/op_struct.py
dcorelib/triqs_compat/plot/__init__.py
dcorelib/triqs_compat/plot/mpl_interface.py
dcorelib/triqs_compat/plot/protocol.py
dcorelib/triqs_compat/utility/__init__.py
dcorelib/triqs_compat/utility/comparison_tests.py
dcorelib/triqs_compat/utility/h5diff.py
dcorelib/triqs_compat/utility/pade_approximants.py
dcorelib-0.4.dist-info/LICENSE
dcorelib-0.4.dist-info/METADATA
dcorelib-0.4.dist-info/WHEEL
dcorelib-0.4.dist-info/top_level.txt
dcorelib-0.4.dist-info/RECORD
