Metadata-Version: 2.1
Name: dcorelib
Version: 0.4
Summary: Backend of DMFT software for CORrelated Electrons
Home-page: https://github.com/shinaoka/dcorelib
Author: H. Shinaoka
Author-email: h.shinaoka@gmail.com
License: UNKNOWN
Keywords: condensed-matter dmft
Platform: UNKNOWN
Classifier: Development Status :: 5 - Production/Stable
Classifier: Intended Audience :: Science/Research
Classifier: Intended Audience :: Developers
Classifier: Topic :: Scientific/Engineering :: Physics
Classifier: Programming Language :: Python :: 3
Requires-Python: >=3.6, <4
License-File: LICENSE
Requires-Dist: numpy
Requires-Dist: scipy
Requires-Dist: h5py
Requires-Dist: mpmath
Requires-Dist: matplotlib
Requires-Dist: irbasis3 (>=3.0a6)
Provides-Extra: dev
Requires-Dist: pytest ; extra == 'dev'
Requires-Dist: matplotlib ; extra == 'dev'
